README.md
setup.py
TOPSIS_Aseem_101803469.egg-info/PKG-INFO
TOPSIS_Aseem_101803469.egg-info/SOURCES.txt
TOPSIS_Aseem_101803469.egg-info/dependency_links.txt
TOPSIS_Aseem_101803469.egg-info/entry_points.txt
TOPSIS_Aseem_101803469.egg-info/requires.txt
TOPSIS_Aseem_101803469.egg-info/top_level.txt
src/topsis.py