Metadata-Version: 2.1
Name: TOPSIS-Aseem-101803469
Version: 3.0.2
Summary: A Python package for implementing TOPSIS technique.
Home-page: https://pypi.org/project/TOPSIS-Aseem-101803469/
Author: Aseem Khullar
Author-email: akhullar_be18@thapar.edu
License: MIT
Platform: UNKNOWN
Classifier: License :: OSI Approved :: MIT License
Classifier: Programming Language :: Python :: 3
Classifier: Programming Language :: Python :: 3.4
Classifier: Programming Language :: Python :: 3.5
Classifier: Programming Language :: Python :: 3.6
Classifier: Programming Language :: Python :: 3.7
